turing_calculator.py
turing_calculator-0.1.0.dist-info/WHEEL
turing_calculator-0.1.0.dist-info/METADATA
turing_calculator-0.1.0.dist-info/RECORD
