Metadata-Version: 2.1
Name: turing_calculator
Version: 0.1.0
Summary: Simple calculator in python
Home-page: https://github.com/keelanjordan/turing_calculator-py
Author: Keelan Jordan
Author-email: keelan@keelanjordan.com
Classifier: License :: OSI Approved :: MIT License
